data_cdk_constructs/__init__.py
data_cdk_constructs/py.typed
data_cdk_constructs/_jsii/__init__.py
data_cdk_constructs/_jsii/data-cdk-constructs@0.0.1.jsii.tgz
data_cdk_constructs-0.0.1.dist-info/LICENSE
data_cdk_constructs-0.0.1.dist-info/METADATA
data_cdk_constructs-0.0.1.dist-info/WHEEL
data_cdk_constructs-0.0.1.dist-info/top_level.txt
data_cdk_constructs-0.0.1.dist-info/RECORD
